<annotation>
	<folder></folder>
	<filename>106812_jpg.rf.fde7f973fb9674dd19fe7cc8f2eac78a.jpg</filename>
	<path>106812_jpg.rf.fde7f973fb9674dd19fe7cc8f2eac78a.jpg</path>
	<source>
		<database>roboflow.ai</database>
	</source>
	<size>
		<width>480</width>
		<height>480</height>
		<depth>3</depth>
	</size>
	<segmented>0</segmented>
	<object>
		<name>Distinct Logo</name>
		<pose>Unspecified</pose>
		<truncated>0</truncated>
		<difficult>0</difficult>
		<occluded>0</occluded>
		<bndbox>
			<xmin>120</xmin>
			<xmax>367</xmax>
			<ymin>112</ymin>
			<ymax>432</ymax>
		</bndbox>
	</object>
	<object>
		<name>TypeWine Type</name>
		<pose>Unspecified</pose>
		<truncated>0</truncated>
		<difficult>0</difficult>
		<occluded>0</occluded>
		<bndbox>
			<xmin>182</xmin>
			<xmax>298</xmax>
			<ymin>357</ymin>
			<ymax>379</ymax>
		</bndbox>
	</object>
	<object>
		<name>Appellation AOC DOC AVARegion</name>
		<pose>Unspecified</pose>
		<truncated>0</truncated>
		<difficult>0</difficult>
		<occluded>0</occluded>
		<bndbox>
			<xmin>128</xmin>
			<xmax>357</xmax>
			<ymin>391</ymin>
			<ymax>429</ymax>
		</bndbox>
	</object>
	<object>
		<name>CountryCountry</name>
		<pose>Unspecified</pose>
		<truncated>0</truncated>
		<difficult>0</difficult>
		<occluded>0</occluded>
		<bndbox>
			<xmin>229</xmin>
			<xmax>283</xmax>
			<ymin>454</ymin>
			<ymax>465</ymax>
		</bndbox>
	</object>
	<object>
		<name>AlcoholPercentage</name>
		<pose>Unspecified</pose>
		<truncated>0</truncated>
		<difficult>0</difficult>
		<occluded>0</occluded>
		<bndbox>
			<xmin>168</xmin>
			<xmax>225</xmax>
			<ymin>456</ymin>
			<ymax>465</ymax>
		</bndbox>
	</object>
	<object>
		<name>Maker-Name</name>
		<pose>Unspecified</pose>
		<truncated>0</truncated>
		<difficult>0</difficult>
		<occluded>0</occluded>
		<bndbox>
			<xmin>122</xmin>
			<xmax>349</xmax>
			<ymin>8</ymin>
			<ymax>113</ymax>
		</bndbox>
	</object>
</annotation>
