<annotation>
	<folder></folder>
	<filename>115532_jpg.rf.9e3eadf089b0e35357af7e17a1bda4cf.jpg</filename>
	<path>115532_jpg.rf.9e3eadf089b0e35357af7e17a1bda4cf.jpg</path>
	<source>
		<database>roboflow.ai</database>
	</source>
	<size>
		<width>767</width>
		<height>767</height>
		<depth>3</depth>
	</size>
	<segmented>0</segmented>
	<object>
		<name>Maker-Name</name>
		<pose>Unspecified</pose>
		<truncated>0</truncated>
		<difficult>0</difficult>
		<occluded>0</occluded>
		<bndbox>
			<xmin>203</xmin>
			<xmax>583</xmax>
			<ymin>121</ymin>
			<ymax>185</ymax>
		</bndbox>
	</object>
	<object>
		<name>TypeWine Type</name>
		<pose>Unspecified</pose>
		<truncated>0</truncated>
		<difficult>0</difficult>
		<occluded>0</occluded>
		<bndbox>
			<xmin>407</xmin>
			<xmax>559</xmax>
			<ymin>429</ymin>
			<ymax>452</ymax>
		</bndbox>
	</object>
	<object>
		<name>Appellation AOC DOC AVARegion</name>
		<pose>Unspecified</pose>
		<truncated>0</truncated>
		<difficult>0</difficult>
		<occluded>0</occluded>
		<bndbox>
			<xmin>448</xmin>
			<xmax>563</xmax>
			<ymin>458</ymin>
			<ymax>475</ymax>
		</bndbox>
	</object>
	<object>
		<name>Distinct Logo</name>
		<pose>Unspecified</pose>
		<truncated>0</truncated>
		<difficult>0</difficult>
		<occluded>0</occluded>
		<bndbox>
			<xmin>128</xmin>
			<xmax>462</xmax>
			<ymin>366</ymin>
			<ymax>759</ymax>
		</bndbox>
	</object>
	<object>
		<name>AlcoholPercentage</name>
		<pose>Unspecified</pose>
		<truncated>0</truncated>
		<difficult>0</difficult>
		<occluded>0</occluded>
		<bndbox>
			<xmin>494</xmin>
			<xmax>623</xmax>
			<ymin>739</ymin>
			<ymax>757</ymax>
		</bndbox>
	</object>
</annotation>
