<annotation>
	<folder></folder>
	<filename>119857_jpg.rf.9afb91f4b6b15850835d5092389d36b7.jpg</filename>
	<path>119857_jpg.rf.9afb91f4b6b15850835d5092389d36b7.jpg</path>
	<source>
		<database>roboflow.ai</database>
	</source>
	<size>
		<width>767</width>
		<height>767</height>
		<depth>3</depth>
	</size>
	<segmented>0</segmented>
	<object>
		<name>CountryCountry</name>
		<pose>Unspecified</pose>
		<truncated>0</truncated>
		<difficult>0</difficult>
		<occluded>0</occluded>
		<bndbox>
			<xmin>217</xmin>
			<xmax>554</xmax>
			<ymin>134</ymin>
			<ymax>180</ymax>
		</bndbox>
	</object>
	<object>
		<name>Distinct Logo</name>
		<pose>Unspecified</pose>
		<truncated>0</truncated>
		<difficult>0</difficult>
		<occluded>0</occluded>
		<bndbox>
			<xmin>319</xmin>
			<xmax>450</xmax>
			<ymin>154</ymin>
			<ymax>288</ymax>
		</bndbox>
	</object>
	<object>
		<name>Maker-Name</name>
		<pose>Unspecified</pose>
		<truncated>0</truncated>
		<difficult>0</difficult>
		<occluded>0</occluded>
		<bndbox>
			<xmin>138</xmin>
			<xmax>629</xmax>
			<ymin>382</ymin>
			<ymax>434</ymax>
		</bndbox>
	</object>
	<object>
		<name>Appellation QualityLevel</name>
		<pose>Unspecified</pose>
		<truncated>0</truncated>
		<difficult>0</difficult>
		<occluded>0</occluded>
		<bndbox>
			<xmin>207</xmin>
			<xmax>556</xmax>
			<ymin>442</ymin>
			<ymax>480</ymax>
		</bndbox>
	</object>
	<object>
		<name>Maker-Name</name>
		<pose>Unspecified</pose>
		<truncated>0</truncated>
		<difficult>0</difficult>
		<occluded>0</occluded>
		<bndbox>
			<xmin>295</xmin>
			<xmax>470</xmax>
			<ymin>563</ymin>
			<ymax>593</ymax>
		</bndbox>
	</object>
	<object>
		<name>CountryCountry</name>
		<pose>Unspecified</pose>
		<truncated>0</truncated>
		<difficult>0</difficult>
		<occluded>0</occluded>
		<bndbox>
			<xmin>608</xmin>
			<xmax>662</xmax>
			<ymin>628</ymin>
			<ymax>649</ymax>
		</bndbox>
	</object>
	<object>
		<name>Maker-Name</name>
		<pose>Unspecified</pose>
		<truncated>0</truncated>
		<difficult>0</difficult>
		<occluded>0</occluded>
		<bndbox>
			<xmin>328</xmin>
			<xmax>534</xmax>
			<ymin>632</ymin>
			<ymax>646</ymax>
		</bndbox>
	</object>
</annotation>
