<annotation>
	<folder></folder>
	<filename>122892_jpg.rf.335a08fef2917f29ce368efbdd485825.jpg</filename>
	<path>122892_jpg.rf.335a08fef2917f29ce368efbdd485825.jpg</path>
	<source>
		<database>roboflow.ai</database>
	</source>
	<size>
		<width>767</width>
		<height>767</height>
		<depth>3</depth>
	</size>
	<segmented>0</segmented>
	<object>
		<name>Appellation QualityLevel</name>
		<pose>Unspecified</pose>
		<truncated>0</truncated>
		<difficult>0</difficult>
		<occluded>0</occluded>
		<bndbox>
			<xmin>231</xmin>
			<xmax>535</xmax>
			<ymin>131</ymin>
			<ymax>171</ymax>
		</bndbox>
	</object>
	<object>
		<name>Distinct Logo</name>
		<pose>Unspecified</pose>
		<truncated>0</truncated>
		<difficult>0</difficult>
		<occluded>0</occluded>
		<bndbox>
			<xmin>78</xmin>
			<xmax>680</xmax>
			<ymin>177</ymin>
			<ymax>405</ymax>
		</bndbox>
	</object>
	<object>
		<name>Maker-Name</name>
		<pose>Unspecified</pose>
		<truncated>0</truncated>
		<difficult>0</difficult>
		<occluded>0</occluded>
		<bndbox>
			<xmin>72</xmin>
			<xmax>690</xmax>
			<ymin>405</ymin>
			<ymax>528</ymax>
		</bndbox>
	</object>
	<object>
		<name>VintageYear</name>
		<pose>Unspecified</pose>
		<truncated>0</truncated>
		<difficult>0</difficult>
		<occluded>0</occluded>
		<bndbox>
			<xmin>322</xmin>
			<xmax>431</xmax>
			<ymin>536</ymin>
			<ymax>568</ymax>
		</bndbox>
	</object>
	<object>
		<name>Appellation AOC DOC AVARegion</name>
		<pose>Unspecified</pose>
		<truncated>0</truncated>
		<difficult>0</difficult>
		<occluded>0</occluded>
		<bndbox>
			<xmin>118</xmin>
			<xmax>413</xmax>
			<ymin>573</ymin>
			<ymax>610</ymax>
		</bndbox>
	</object>
	<object>
		<name>Appellation QualityLevel</name>
		<pose>Unspecified</pose>
		<truncated>0</truncated>
		<difficult>0</difficult>
		<occluded>0</occluded>
		<bndbox>
			<xmin>421</xmin>
			<xmax>651</xmax>
			<ymin>573</ymin>
			<ymax>610</ymax>
		</bndbox>
	</object>
</annotation>
