<annotation>
	<folder></folder>
	<filename>124983_jpg.rf.bc33584883e571d0fd179145e3ea29bf.jpg</filename>
	<path>124983_jpg.rf.bc33584883e571d0fd179145e3ea29bf.jpg</path>
	<source>
		<database>roboflow.ai</database>
	</source>
	<size>
		<width>767</width>
		<height>767</height>
		<depth>3</depth>
	</size>
	<segmented>0</segmented>
	<object>
		<name>Maker-Name</name>
		<pose>Unspecified</pose>
		<truncated>0</truncated>
		<difficult>0</difficult>
		<occluded>0</occluded>
		<bndbox>
			<xmin>256</xmin>
			<xmax>525</xmax>
			<ymin>257</ymin>
			<ymax>368</ymax>
		</bndbox>
	</object>
	<object>
		<name>Appellation AOC DOC AVARegion</name>
		<pose>Unspecified</pose>
		<truncated>0</truncated>
		<difficult>0</difficult>
		<occluded>0</occluded>
		<bndbox>
			<xmin>275</xmin>
			<xmax>482</xmax>
			<ymin>640</ymin>
			<ymax>666</ymax>
		</bndbox>
	</object>
	<object>
		<name>AlcoholPercentage</name>
		<pose>Unspecified</pose>
		<truncated>0</truncated>
		<difficult>0</difficult>
		<occluded>0</occluded>
		<bndbox>
			<xmin>615</xmin>
			<xmax>638</xmax>
			<ymin>611</ymin>
			<ymax>716</ymax>
		</bndbox>
	</object>
	<object>
		<name>Maker-Name</name>
		<pose>Unspecified</pose>
		<truncated>0</truncated>
		<difficult>0</difficult>
		<occluded>0</occluded>
		<bndbox>
			<xmin>205</xmin>
			<xmax>557</xmax>
			<ymin>680</ymin>
			<ymax>701</ymax>
		</bndbox>
	</object>
</annotation>
