<annotation>
	<folder></folder>
	<filename>134765_jpg.rf.2298496008a1aa5a2a3ca7196ee17114.jpg</filename>
	<path>134765_jpg.rf.2298496008a1aa5a2a3ca7196ee17114.jpg</path>
	<source>
		<database>roboflow.ai</database>
	</source>
	<size>
		<width>767</width>
		<height>767</height>
		<depth>3</depth>
	</size>
	<segmented>0</segmented>
	<object>
		<name>Distinct Logo</name>
		<pose>Unspecified</pose>
		<truncated>0</truncated>
		<difficult>0</difficult>
		<occluded>0</occluded>
		<bndbox>
			<xmin>360</xmin>
			<xmax>416</xmax>
			<ymin>121</ymin>
			<ymax>172</ymax>
		</bndbox>
	</object>
	<object>
		<name>Maker-Name</name>
		<pose>Unspecified</pose>
		<truncated>0</truncated>
		<difficult>0</difficult>
		<occluded>0</occluded>
		<bndbox>
			<xmin>206</xmin>
			<xmax>566</xmax>
			<ymin>176</ymin>
			<ymax>245</ymax>
		</bndbox>
	</object>
	<object>
		<name>Distinct Logo</name>
		<pose>Unspecified</pose>
		<truncated>0</truncated>
		<difficult>0</difficult>
		<occluded>0</occluded>
		<bndbox>
			<xmin>287</xmin>
			<xmax>489</xmax>
			<ymin>248</ymin>
			<ymax>411</ymax>
		</bndbox>
	</object>
	<object>
		<name>Maker-Name</name>
		<pose>Unspecified</pose>
		<truncated>0</truncated>
		<difficult>0</difficult>
		<occluded>0</occluded>
		<bndbox>
			<xmin>239</xmin>
			<xmax>544</xmax>
			<ymin>432</ymin>
			<ymax>489</ymax>
		</bndbox>
	</object>
	<object>
		<name>TypeWine Type</name>
		<pose>Unspecified</pose>
		<truncated>0</truncated>
		<difficult>0</difficult>
		<occluded>0</occluded>
		<bndbox>
			<xmin>289</xmin>
			<xmax>478</xmax>
			<ymin>507</ymin>
			<ymax>537</ymax>
		</bndbox>
	</object>
	<object>
		<name>VintageYear</name>
		<pose>Unspecified</pose>
		<truncated>0</truncated>
		<difficult>0</difficult>
		<occluded>0</occluded>
		<bndbox>
			<xmin>348</xmin>
			<xmax>420</xmax>
			<ymin>544</ymin>
			<ymax>566</ymax>
		</bndbox>
	</object>
	<object>
		<name>Appellation AOC DOC AVARegion</name>
		<pose>Unspecified</pose>
		<truncated>0</truncated>
		<difficult>0</difficult>
		<occluded>0</occluded>
		<bndbox>
			<xmin>281</xmin>
			<xmax>492</xmax>
			<ymin>573</ymin>
			<ymax>600</ymax>
		</bndbox>
	</object>
</annotation>
