<annotation>
	<folder></folder>
	<filename>79724_jpg.rf.f179684817f0ec7368d8520c20995c89.jpg</filename>
	<path>79724_jpg.rf.f179684817f0ec7368d8520c20995c89.jpg</path>
	<source>
		<database>roboflow.ai</database>
	</source>
	<size>
		<width>479</width>
		<height>434</height>
		<depth>3</depth>
	</size>
	<segmented>0</segmented>
	<object>
		<name>Distinct Logo</name>
		<pose>Unspecified</pose>
		<truncated>0</truncated>
		<difficult>0</difficult>
		<occluded>0</occluded>
		<bndbox>
			<xmin>110</xmin>
			<xmax>370</xmax>
			<ymin>225</ymin>
			<ymax>412</ymax>
		</bndbox>
	</object>
	<object>
		<name>Maker-Name</name>
		<pose>Unspecified</pose>
		<truncated>0</truncated>
		<difficult>0</difficult>
		<occluded>0</occluded>
		<bndbox>
			<xmin>78</xmin>
			<xmax>408</xmax>
			<ymin>17</ymin>
			<ymax>49</ymax>
		</bndbox>
	</object>
	<object>
		<name>Distinct Logo</name>
		<pose>Unspecified</pose>
		<truncated>0</truncated>
		<difficult>0</difficult>
		<occluded>0</occluded>
		<bndbox>
			<xmin>22</xmin>
			<xmax>86</xmax>
			<ymin>355</ymin>
			<ymax>410</ymax>
		</bndbox>
	</object>
	<object>
		<name>VintageYear</name>
		<pose>Unspecified</pose>
		<truncated>0</truncated>
		<difficult>0</difficult>
		<occluded>0</occluded>
		<bndbox>
			<xmin>401</xmin>
			<xmax>455</xmax>
			<ymin>394</ymin>
			<ymax>411</ymax>
		</bndbox>
	</object>
	<object>
		<name>TypeWine Type</name>
		<pose>Unspecified</pose>
		<truncated>0</truncated>
		<difficult>0</difficult>
		<occluded>0</occluded>
		<bndbox>
			<xmin>188</xmin>
			<xmax>292</xmax>
			<ymin>89</ymin>
			<ymax>109</ymax>
		</bndbox>
	</object>
</annotation>
