<annotation>
	<folder></folder>
	<filename>87036_jpg.rf.c4ef60c33d6e2968a6afe36f3edba3d8.jpg</filename>
	<path>87036_jpg.rf.c4ef60c33d6e2968a6afe36f3edba3d8.jpg</path>
	<source>
		<database>roboflow.ai</database>
	</source>
	<size>
		<width>480</width>
		<height>561</height>
		<depth>3</depth>
	</size>
	<segmented>0</segmented>
	<object>
		<name>Distinct Logo</name>
		<pose>Unspecified</pose>
		<truncated>0</truncated>
		<difficult>0</difficult>
		<occluded>0</occluded>
		<bndbox>
			<xmin>32</xmin>
			<xmax>481</xmax>
			<ymin>107</ymin>
			<ymax>463</ymax>
		</bndbox>
	</object>
	<object>
		<name>Maker-Name</name>
		<pose>Unspecified</pose>
		<truncated>0</truncated>
		<difficult>0</difficult>
		<occluded>0</occluded>
		<bndbox>
			<xmin>253</xmin>
			<xmax>436</xmax>
			<ymin>15</ymin>
			<ymax>57</ymax>
		</bndbox>
	</object>
	<object>
		<name>VintageYear</name>
		<pose>Unspecified</pose>
		<truncated>0</truncated>
		<difficult>0</difficult>
		<occluded>0</occluded>
		<bndbox>
			<xmin>22</xmin>
			<xmax>103</xmax>
			<ymin>522</ymin>
			<ymax>549</ymax>
		</bndbox>
	</object>
	<object>
		<name>CountryCountry</name>
		<pose>Unspecified</pose>
		<truncated>0</truncated>
		<difficult>0</difficult>
		<occluded>0</occluded>
		<bndbox>
			<xmin>391</xmin>
			<xmax>446</xmax>
			<ymin>528</ymin>
			<ymax>548</ymax>
		</bndbox>
	</object>
	<object>
		<name>TypeWine Type</name>
		<pose>Unspecified</pose>
		<truncated>0</truncated>
		<difficult>0</difficult>
		<occluded>0</occluded>
		<bndbox>
			<xmin>134</xmin>
			<xmax>207</xmax>
			<ymin>529</ymin>
			<ymax>548</ymax>
		</bndbox>
	</object>
</annotation>
