<annotation>
	<folder></folder>
	<filename>96768_jpg.rf.521e12968b8165ad460d1d5c2c776b01.jpg</filename>
	<path>96768_jpg.rf.521e12968b8165ad460d1d5c2c776b01.jpg</path>
	<source>
		<database>roboflow.ai</database>
	</source>
	<size>
		<width>767</width>
		<height>767</height>
		<depth>3</depth>
	</size>
	<segmented>0</segmented>
	<object>
		<name>Distinct Logo</name>
		<pose>Unspecified</pose>
		<truncated>0</truncated>
		<difficult>0</difficult>
		<occluded>0</occluded>
		<bndbox>
			<xmin>324</xmin>
			<xmax>451</xmax>
			<ymin>174</ymin>
			<ymax>245</ymax>
		</bndbox>
	</object>
	<object>
		<name>Established YearYear</name>
		<pose>Unspecified</pose>
		<truncated>0</truncated>
		<difficult>0</difficult>
		<occluded>0</occluded>
		<bndbox>
			<xmin>476</xmin>
			<xmax>579</xmax>
			<ymin>285</ymin>
			<ymax>308</ymax>
		</bndbox>
	</object>
	<object>
		<name>Appellation QualityLevel</name>
		<pose>Unspecified</pose>
		<truncated>0</truncated>
		<difficult>0</difficult>
		<occluded>0</occluded>
		<bndbox>
			<xmin>189</xmin>
			<xmax>467</xmax>
			<ymin>287</ymin>
			<ymax>312</ymax>
		</bndbox>
	</object>
	<object>
		<name>Maker-Name</name>
		<pose>Unspecified</pose>
		<truncated>0</truncated>
		<difficult>0</difficult>
		<occluded>0</occluded>
		<bndbox>
			<xmin>99</xmin>
			<xmax>676</xmax>
			<ymin>340</ymin>
			<ymax>417</ymax>
		</bndbox>
	</object>
	<object>
		<name>VintageYear</name>
		<pose>Unspecified</pose>
		<truncated>0</truncated>
		<difficult>0</difficult>
		<occluded>0</occluded>
		<bndbox>
			<xmin>349</xmin>
			<xmax>432</xmax>
			<ymin>476</ymin>
			<ymax>503</ymax>
		</bndbox>
	</object>
	<object>
		<name>Maker-Name</name>
		<pose>Unspecified</pose>
		<truncated>0</truncated>
		<difficult>0</difficult>
		<occluded>0</occluded>
		<bndbox>
			<xmin>274</xmin>
			<xmax>511</xmax>
			<ymin>527</ymin>
			<ymax>559</ymax>
		</bndbox>
	</object>
</annotation>
