<annotation>
	<folder></folder>
	<filename>97065_jpg.rf.a7237d36219be9eed69be158d980fd23.jpg</filename>
	<path>97065_jpg.rf.a7237d36219be9eed69be158d980fd23.jpg</path>
	<source>
		<database>roboflow.ai</database>
	</source>
	<size>
		<width>480</width>
		<height>511</height>
		<depth>3</depth>
	</size>
	<segmented>0</segmented>
	<object>
		<name>Sweetness-Brut-SecSweetness-Brut-Sec</name>
		<pose>Unspecified</pose>
		<truncated>0</truncated>
		<difficult>0</difficult>
		<occluded>0</occluded>
		<bndbox>
			<xmin>198</xmin>
			<xmax>285</xmax>
			<ymin>125</ymin>
			<ymax>147</ymax>
		</bndbox>
	</object>
	<object>
		<name>TypeWine Type</name>
		<pose>Unspecified</pose>
		<truncated>0</truncated>
		<difficult>0</difficult>
		<occluded>0</occluded>
		<bndbox>
			<xmin>115</xmin>
			<xmax>361</xmax>
			<ymin>214</ymin>
			<ymax>287</ymax>
		</bndbox>
	</object>
	<object>
		<name>Appellation AOC DOC AVARegion</name>
		<pose>Unspecified</pose>
		<truncated>0</truncated>
		<difficult>0</difficult>
		<occluded>0</occluded>
		<bndbox>
			<xmin>167</xmin>
			<xmax>315</xmax>
			<ymin>357</ymin>
			<ymax>418</ymax>
		</bndbox>
	</object>
	<object>
		<name>Maker-Name</name>
		<pose>Unspecified</pose>
		<truncated>0</truncated>
		<difficult>0</difficult>
		<occluded>0</occluded>
		<bndbox>
			<xmin>122</xmin>
			<xmax>354</xmax>
			<ymin>84</ymin>
			<ymax>117</ymax>
		</bndbox>
	</object>
</annotation>
