<annotation>
	<folder></folder>
	<filename>98124_jpg.rf.9a5268615ca33e22161360f948e4b2f4.jpg</filename>
	<path>98124_jpg.rf.9a5268615ca33e22161360f948e4b2f4.jpg</path>
	<source>
		<database>roboflow.ai</database>
	</source>
	<size>
		<width>767</width>
		<height>767</height>
		<depth>3</depth>
	</size>
	<segmented>0</segmented>
	<object>
		<name>Distinct Logo</name>
		<pose>Unspecified</pose>
		<truncated>0</truncated>
		<difficult>0</difficult>
		<occluded>0</occluded>
		<bndbox>
			<xmin>285</xmin>
			<xmax>487</xmax>
			<ymin>29</ymin>
			<ymax>217</ymax>
		</bndbox>
	</object>
	<object>
		<name>Maker-Name</name>
		<pose>Unspecified</pose>
		<truncated>0</truncated>
		<difficult>0</difficult>
		<occluded>0</occluded>
		<bndbox>
			<xmin>286</xmin>
			<xmax>485</xmax>
			<ymin>249</ymin>
			<ymax>280</ymax>
		</bndbox>
	</object>
	<object>
		<name>Distinct Logo</name>
		<pose>Unspecified</pose>
		<truncated>0</truncated>
		<difficult>0</difficult>
		<occluded>0</occluded>
		<bndbox>
			<xmin>325</xmin>
			<xmax>443</xmax>
			<ymin>339</ymin>
			<ymax>438</ymax>
		</bndbox>
	</object>
	<object>
		<name>VintageYear</name>
		<pose>Unspecified</pose>
		<truncated>0</truncated>
		<difficult>0</difficult>
		<occluded>0</occluded>
		<bndbox>
			<xmin>362</xmin>
			<xmax>412</xmax>
			<ymin>506</ymin>
			<ymax>525</ymax>
		</bndbox>
	</object>
	<object>
		<name>TypeWine Type</name>
		<pose>Unspecified</pose>
		<truncated>0</truncated>
		<difficult>0</difficult>
		<occluded>0</occluded>
		<bndbox>
			<xmin>303</xmin>
			<xmax>471</xmax>
			<ymin>544</ymin>
			<ymax>597</ymax>
		</bndbox>
	</object>
	<object>
		<name>Appellation AOC DOC AVARegion</name>
		<pose>Unspecified</pose>
		<truncated>0</truncated>
		<difficult>0</difficult>
		<occluded>0</occluded>
		<bndbox>
			<xmin>304</xmin>
			<xmax>469</xmax>
			<ymin>618</ymin>
			<ymax>643</ymax>
		</bndbox>
	</object>
	<object>
		<name>Maker-Name</name>
		<pose>Unspecified</pose>
		<truncated>0</truncated>
		<difficult>0</difficult>
		<occluded>0</occluded>
		<bndbox>
			<xmin>268</xmin>
			<xmax>503</xmax>
			<ymin>679</ymin>
			<ymax>701</ymax>
		</bndbox>
	</object>
	<object>
		<name>AlcoholPercentage</name>
		<pose>Unspecified</pose>
		<truncated>0</truncated>
		<difficult>0</difficult>
		<occluded>0</occluded>
		<bndbox>
			<xmin>329</xmin>
			<xmax>458</xmax>
			<ymin>738</ymin>
			<ymax>759</ymax>
		</bndbox>
	</object>
</annotation>
